betacloud/__init__.py
betacloud/__main__.py
betacloud/main.py
betacloud/version.py
betacloud-0.0.2.dist-info/LICENSE
betacloud-0.0.2.dist-info/METADATA
betacloud-0.0.2.dist-info/WHEEL
betacloud-0.0.2.dist-info/entry_points.txt
betacloud-0.0.2.dist-info/namespace_packages.txt
betacloud-0.0.2.dist-info/top_level.txt
betacloud-0.0.2.dist-info/RECORD
